src/__init__.py
src/cli.py
src/dataGene.py
src/transpoter.py
src/utility.py
dthok-1.0.0.dist-info/LICENSE
dthok-1.0.0.dist-info/METADATA
dthok-1.0.0.dist-info/WHEEL
dthok-1.0.0.dist-info/entry_points.txt
dthok-1.0.0.dist-info/top_level.txt
dthok-1.0.0.dist-info/RECORD
