Metadata-Version: 2.1
Name: dthok
Version: 1.0.0
Summary: Bulk Test Data Generator
Home-page: https://github.com/paloitsingapore/dthok
Author: Palo IT Singapore
Author-email: SG-PyPi-Group@sg.palo-it.com
License: MIT license
Keywords: dthok
Platform: UNKNOWN
Classifier: Intended Audience :: Developers
Classifier: License :: OSI Approved :: MIT License
Classifier: Natural Language :: English
Classifier: Programming Language :: Python :: 3
Classifier: Programming Language :: Python :: 3.6
Classifier: Programming Language :: Python :: 3.7
Classifier: Programming Language :: Python :: 3.8
Requires-Python: >=3.6
Requires-Dist: Faker
Requires-Dist: randominfo
Requires-Dist: dict2xml
Requires-Dist: json2xml
Requires-Dist: xmltodict
Requires-Dist: phone-gen
